collibra_search/__init__.py
collibra_search/api_client.py
collibra_search/configuration.py
collibra_search/exceptions.py
collibra_search/rest.py
collibra_search/api/__init__.py
collibra_search/api/search_api.py
collibra_search/models/__init__.py
collibra_search/models/find_search_views_request.py
collibra_search/models/paged_response_search_view.py
collibra_search/models/search_aggregation.py
collibra_search/models/search_asset_result_resource.py
collibra_search/models/search_asset_result_resource_all_of.py
collibra_search/models/search_community_result_resource.py
collibra_search/models/search_domain_result_resource.py
collibra_search/models/search_domain_result_resource_all_of.py
collibra_search/models/search_filter.py
collibra_search/models/search_highlight.py
collibra_search/models/search_in_fields.py
collibra_search/models/search_request.py
collibra_search/models/search_response.py
collibra_search/models/search_response_aggregation.py
collibra_search/models/search_response_aggregation_value.py
collibra_search/models/search_result.py
collibra_search/models/search_result_highlight.py
collibra_search/models/search_result_resource.py
collibra_search/models/search_result_status.py
collibra_search/models/search_result_type.py
collibra_search/models/search_user_group_result_resource.py
collibra_search/models/search_user_result_resource.py
collibra_search/models/search_view.py
collibra_search/models/search_view_paged_response.py
collibra_search-2.0.0.post5.dist-info/METADATA
collibra_search-2.0.0.post5.dist-info/WHEEL
collibra_search-2.0.0.post5.dist-info/top_level.txt
collibra_search-2.0.0.post5.dist-info/RECORD
